dronecan_gui_tool/__init__.py
dronecan_gui_tool/active_data_type_detector.py
dronecan_gui_tool/main.py
dronecan_gui_tool/setup_window.py
dronecan_gui_tool/version.py
dronecan_gui_tool/icons/dronecan_gui_tool.png
dronecan_gui_tool/icons/logo.ico
dronecan_gui_tool/panels/RTK_panel.py
dronecan_gui_tool/panels/RemoteID_panel.py
dronecan_gui_tool/panels/__init__.py
dronecan_gui_tool/panels/actuator_panel.py
dronecan_gui_tool/panels/esc_panel.py
dronecan_gui_tool/panels/hobbywing_esc.py
dronecan_gui_tool/panels/rc_panel.py
dronecan_gui_tool/panels/rtcm3.py
dronecan_gui_tool/panels/serial_panel.py
dronecan_gui_tool/panels/stats_panel.py
dronecan_gui_tool/widgets/__init__.py
dronecan_gui_tool/widgets/about_window.py
dronecan_gui_tool/widgets/console.py
dronecan_gui_tool/widgets/directory_selection.py
dronecan_gui_tool/widgets/dynamic_node_id_allocator.py
dronecan_gui_tool/widgets/file_server.py
dronecan_gui_tool/widgets/local_node.py
dronecan_gui_tool/widgets/log_message_display.py
dronecan_gui_tool/widgets/node_monitor.py
dronecan_gui_tool/widgets/node_properties.py
dronecan_gui_tool/widgets/subscriber.py
dronecan_gui_tool/widgets/table_display.py
dronecan_gui_tool/widgets/bus_monitor/__init__.py
dronecan_gui_tool/widgets/bus_monitor/transfer_decoder.py
dronecan_gui_tool/widgets/bus_monitor/window.py
dronecan_gui_tool/widgets/can_adapter_control_panel/__init__.py
dronecan_gui_tool/widgets/can_adapter_control_panel/slcan_cli.py
dronecan_gui_tool/widgets/plotter/__init__.py
dronecan_gui_tool/widgets/plotter/plot_container.py
dronecan_gui_tool/widgets/plotter/value_extractor.py
dronecan_gui_tool/widgets/plotter/value_extractor_views.py
dronecan_gui_tool/widgets/plotter/window.py
dronecan_gui_tool/widgets/plotter/plot_areas/__init__.py
dronecan_gui_tool/widgets/plotter/plot_areas/xy.py
dronecan_gui_tool/widgets/plotter/plot_areas/yt.py
dronecan_gui_tool-1.2.27.data/data/share/applications/DroneCAN GUI Tool.desktop
dronecan_gui_tool-1.2.27.dist-info/LICENSE
dronecan_gui_tool-1.2.27.dist-info/METADATA
dronecan_gui_tool-1.2.27.dist-info/WHEEL
dronecan_gui_tool-1.2.27.dist-info/entry_points.txt
dronecan_gui_tool-1.2.27.dist-info/top_level.txt
dronecan_gui_tool-1.2.27.dist-info/RECORD
